debspawn/__init__.py
debspawn/aptcache.py
debspawn/build.py
debspawn/cli.py
debspawn/config.py
debspawn/dsrun
debspawn/injectpkg.py
debspawn/maintain.py
debspawn/nspawn.py
debspawn/osbase.py
debspawn/utils/__init__.py
debspawn/utils/command.py
debspawn/utils/env.py
debspawn/utils/log.py
debspawn/utils/misc.py
debspawn/utils/zstd_tar.py
debspawn-0.4.3.data/scripts/debspawn
debspawn-0.4.3.dist-info/AUTHORS
debspawn-0.4.3.dist-info/LICENSE
debspawn-0.4.3.dist-info/METADATA
debspawn-0.4.3.dist-info/WHEEL
debspawn-0.4.3.dist-info/top_level.txt
debspawn-0.4.3.dist-info/RECORD
