Metadata-Version: 2.1
Name: debspawn
Version: 0.4.3
Summary: Build Debian packages automatically or interactively in systemd-nspawn containers
Home-page: https://github.com/lkhq/debspawn
Author: Matthias Klumpp
Author-email: matthias@tenstral.net
License: LGPL-3.0+
Platform: any
Requires-Python: >=3.9
Requires-Dist: toml (>=0.10)
